office/__init__.py
office/api/__init__.py
office/api/email.py
office/api/excel.py
office/api/file.py
office/api/finance.py
office/api/image.py
office/api/markdown.py
office/api/ocr.py
office/api/pdf.py
office/api/ppt.py
office/api/tools.py
office/api/video.py
office/api/web.py
office/api/wechat.py
office/api/word.py
office/api/testApi/__init__.py
office/api/testApi/ruiming.py
office/core/__init__.py
office/core/TestTypes/RuimingType.py
office/core/TestTypes/__init__.py
office/lib/__init__.py
office/lib/conf/CONST.py
office/lib/conf/__init__.py
office/lib/decorator_utils/__init__.py
office/lib/decorator_utils/instruction_url.py
office/lib/excel/SplitExcel.py
office/lib/excel/__init__.py
office/lib/image/__init__.py
office/lib/image/add_watermark_service.py
office/lib/image/eliminate_background.py
office/lib/pdf/__init__.py
office/lib/pdf/add_watermark_service.py
office/lib/ppt/__init__.py
office/lib/ppt/ppt2pdf_service.py
office/lib/tools/__init__.py
office/lib/tools/lottery8ticket.py
office/lib/tools/pwd4wifi_service.py
office/lib/tools/qoute_dict_create_article.py
office/lib/tools/weather_city_code.py
office/lib/tools/weather_service.py
office/lib/utils/__init__.py
office/lib/utils/except_utils.py
office/lib/utils/pandas_mem.py
office/lib/utils/time_utils.py
tests/__init__.py
tests/test_main.py
tests/test_code/__init__.py
tests/test_code/test_dev.py
tests/test_code/test_excel.py
tests/test_code/test_file.py
tests/test_code/test_image.py
tests/test_code/test_markdown.py
tests/test_code/test_ocr.py
tests/test_code/test_pdf.py
tests/test_code/test_ppt.py
tests/test_code/test_ruiming.py
tests/test_code/test_search_by_content.py
tests/test_code/test_tools.py
tests/test_code/test_tools1.py
tests/test_code/test_video.py
tests/test_code/test_web.py
tests/test_code/test_wechat.py
tests/test_code/test_word.py
python_office-1.0.5.dist-info/LICENSE
python_office-1.0.5.dist-info/METADATA
python_office-1.0.5.dist-info/WHEEL
python_office-1.0.5.dist-info/top_level.txt
python_office-1.0.5.dist-info/RECORD
