Metadata-Version: 2.1
Name: python-office
Version: 1.0.5
Summary: www.python-office.com
Home-page: https://github.com/CoderWanFeng/python-office
Author: CoderWanFeng
Author-email: 1957875073@qq.com
License: Apache-2.0 license
Project-URL: Bug Tracker, https://github.com/CoderWanFeng/python-office/issues
Project-URL: Documentation, https://github.com/CoderWanFeng/python-office/blob/main/README.md
Project-URL: Source Code, https://github.com/CoderWanFeng/python-office
Platform: any
Requires-Python: >=3.6
License-File: LICENSE
Requires-Dist: rich >=9.13.0
Requires-Dist: you-get
Requires-Dist: poimage
Requires-Dist: poexcel
Requires-Dist: pofile
Requires-Dist: popdf
Requires-Dist: wftools
Requires-Dist: povideo
Requires-Dist: poprogress
Requires-Dist: poocr
Requires-Dist: pocode
Requires-Dist: poemail
Requires-Dist: pospider
Requires-Dist: loguru
Requires-Dist: pomarkdown
Requires-Dist: poppt ; platform_system == "Windows"
Requires-Dist: poword ; platform_system == "Windows"
Requires-Dist: search4file ; platform_system == "Windows"
Requires-Dist: PyOfficeRobot ; platform_system == "Windows"
